MANIFEST.in
README
setup.py
svargaext/__init__.py
svargaext.sqlamigrate.egg-info/PKG-INFO
svargaext.sqlamigrate.egg-info/SOURCES.txt
svargaext.sqlamigrate.egg-info/dependency_links.txt
svargaext.sqlamigrate.egg-info/namespace_packages.txt
svargaext.sqlamigrate.egg-info/requires.txt
svargaext.sqlamigrate.egg-info/top_level.txt
svargaext/sqlamigrate/__init__.py
svargaext/sqlamigrate/apps.py
svargaext/sqlamigrate/codegen.py
svargaext/sqlamigrate/commands.py
svargaext/sqlamigrate/files.py
svargaext/sqlamigrate/smhacks.py
svargaext/sqlamigrate/tabledump.py
svargaext/sqlamigrate/utils.py
svargaext/sqlamigrate/templates/__init__.py
svargaext/sqlamigrate/templates/default.py_tmpl
svargaext/sqlamigrate/templates/migrate.py_tmpl
svargaext/sqlamigrate/templates/script.py_tmpl