Metadata-Version: 1.0
Name: svargaext.sqlamigrate
Version: 0.4
Summary: SQLAlchemy migrate module for Svarga framework
Home-page: http://bitbucket.org/joes/svargaext.sqlamigrate/
Author: Serge S. Koval
Author-email: joes@svargahq.net
License: BSD
Platform: any
Classifier: Development Status :: 4 - Beta
Classifier: Environment :: Web Environment
Classifier: Intended Audience :: Developers
Classifier: License :: OSI Approved :: BSD License
Classifier: Operating System :: OS Independent
Classifier: Programming Language :: Python
Classifier: Topic :: Internet :: WWW/HTTP :: Dynamic Content
Classifier: Topic :: Software Development :: Libraries :: Python Modules
